{"nombre":"dw","total":"30","telefono":"","dicreccion":"","comentarios":"","costo_envio":30,"orden":{"2":["Acelga arcoiris[|]EL RENACER DEL CAMPO ( @elrenacerdelcampo)",0,"$16.00"],"3":["Aguacate[|]EL RENACER DEL CAMPO ( @elrenacerdelcampo)",0,"$99.00"],"4":["Algafita[|]EL RENACER DEL CAMPO ( @elrenacerdelcampo)",0,"$16.00"],"5":["Apio verde[|]EL RENACER DEL CAMPO ( @elrenacerdelcampo)",0,"$16.00"],"6":["Berros[|]EL RENACER DEL CAMPO ( @elrenacerdelcampo)",0,"$16.00"],"7":["Betabel amarillo (500gr)[|]EL RENACER DEL CAMPO ( @elrenacerdelcampo)",0,"$16.00"],"8":["Betabel rojo (500 gr)[|]EL RENACER DEL CAMPO ( @elrenacerdelcampo)",0,"$16.00"],"9":["Chícharo[|]EL RENACER DEL CAMPO ( @elrenacerdelcampo)",0,"$49.00"],"10":["Cilantro[|]EL RENACER DEL CAMPO ( @elrenacerdelcampo)",0,"$16.00"],"11":["Col verde[|]EL RENACER DEL CAMPO ( @elrenacerdelcampo)",0,"$20.00"],"12":["Colinabo[|]EL RENACER DEL CAMPO ( @elrenacerdelcampo)",0,"$20.00"],"13":["Crema[|]EL RENACER DEL CAMPO ( @elrenacerdelcampo)",0,"$123.00"],"14":["Haba verde[|]EL RENACER DEL CAMPO ( @elrenacerdelcampo)",0,"$49.00"],"15":["Kale rizado verde y morado[|]EL RENACER DEL CAMPO ( @elrenacerdelcampo)",0,"$16.00"],"16":["Kale toscano[|]EL RENACER DEL CAMPO ( @elrenacerdelcampo)",0,"$16.00"],"17":["Lechuga[|]EL RENACER DEL CAMPO ( @elrenacerdelcampo)",0,"$16.00"],"18":["Nopales sin espinas[|]EL RENACER DEL CAMPO ( @elrenacerdelcampo)",0,"$3.00"],"19":["Ortiga[|]EL RENACER DEL CAMPO ( @elrenacerdelcampo)",0,"$16.00"],"20":["Pan de masa madre 700 gr[|]EL RENACER DEL CAMPO ( @elrenacerdelcampo)",0,"$82.00"],"21":["Pan de pulque[|]EL RENACER DEL CAMPO ( @elrenacerdelcampo)",0,"$20.00"],"22":["Pay de Requesón[|]EL RENACER DEL CAMPO ( @elrenacerdelcampo)",0,"$148.00"],"23":["Pollo Libre Pastoreo ( Aprox. 2K)[|]EL RENACER DEL CAMPO ( @elrenacerdelcampo)",0,"$359.00"],"24":["Quelites[|]EL RENACER DEL CAMPO ( @elrenacerdelcampo)",0,"$16.00"],"25":["Queso Asadero (450gr)[|]EL RENACER DEL CAMPO ( @elrenacerdelcampo)",0,"$148.00"],"26":["Rábano sandía[|]EL RENACER DEL CAMPO ( @elrenacerdelcampo)",0,"$16.00"],"27":["Requesón[|]EL RENACER DEL CAMPO ( @elrenacerdelcampo)",0,"$74.00"],"28":["Setas Rosas[|]EL RENACER DEL CAMPO ( @elrenacerdelcampo)",0,"$41.00"],"29":["Sopes[|]EL RENACER DEL CAMPO ( @elrenacerdelcampo)",0,"$25.00"],"30":["Tortillas[|]EL RENACER DEL CAMPO ( @elrenacerdelcampo)",0,"$25.00"],"31":["Yogurt[|]EL RENACER DEL CAMPO ( @elrenacerdelcampo)",0,"$58.00"],"32":["Ajo morado (Cabeza)[|]AGROELITE (FB: @AgroeliteMexico)",0,"$11.00"],"33":["Arroz integral[|]AGROELITE (FB: @AgroeliteMexico)",0,"$50.00"],"34":["Arúgula[|]AGROELITE (FB: @AgroeliteMexico)",0,"$11.00"],"35":["BlueBerry[|]AGROELITE (FB: @AgroeliteMexico)",0,"$90.00"],"36":["Brocoli[|]AGROELITE (FB: @AgroeliteMexico)",0,"$19.00"],"37":["Calabacita Italiana[|]AGROELITE (FB: @AgroeliteMexico)",0,"$36.00"],"38":["Calabaza Mantequilla[|]AGROELITE (FB: @AgroeliteMexico)",0,"$100.00"],"39":["Cebolla Blanca[|]AGROELITE (FB: @AgroeliteMexico)",0,"$26.00"],"40":["Chalote (80gr)[|]AGROELITE (FB: @AgroeliteMexico)",0,"$13.00"],"41":["Champignon Cremini[|]AGROELITE (FB: @AgroeliteMexico)",0,"$54.00"],"42":["Ciruela Roja[|]AGROELITE (FB: @AgroeliteMexico)",0,"$34.00"],"43":["Espárrago (500 gr)[|]AGROELITE (FB: @AgroeliteMexico)",0,"$107.00"],"44":["Espinaca baby[|]AGROELITE (FB: @AgroeliteMexico)",0,"$71.00"],"45":["Flor de Calabaza[|]AGROELITE (FB: @AgroeliteMexico)",0,"$36.00"],"46":["Fresa[|]AGROELITE (FB: @AgroeliteMexico)",0,"$28.00"],"47":["Frijoles negros[|]AGROELITE (FB: @AgroeliteMexico)",0,"$46.00"],"48":["Guayaba[|]AGROELITE (FB: @AgroeliteMexico)",0,"$21.00"],"49":["Hinojo de Bulbo[|]AGROELITE (FB: @AgroeliteMexico)",0,"$54.00"],"50":["Hongo Portobello[|]AGROELITE (FB: @AgroeliteMexico)",0,"$86.00"],"51":["Huitlacoche[|]AGROELITE (FB: @AgroeliteMexico)",0,"$41.00"],"52":["Jengibre[|]AGROELITE (FB: @AgroeliteMexico)",0,"$64.00"],"53":["Jitomate Saladette[|]AGROELITE (FB: @AgroeliteMexico)",0,"$43.00"],"54":["Limón Amarillo[|]AGROELITE (FB: @AgroeliteMexico)",0,"$129.00"],"55":["Limón Verde con semilla[|]AGROELITE (FB: @AgroeliteMexico)",0,"$36.00"],"56":["Mango Ataulfo[|]AGROELITE (FB: @AgroeliteMexico)",0,"$31.00"],"57":["Manzana[|]AGROELITE (FB: @AgroeliteMexico)",0,"$39.00"],"58":["Papa Alpha[|]AGROELITE (FB: @AgroeliteMexico)",0,"$36.00"],"59":["Pepino[|]AGROELITE (FB: @AgroeliteMexico)",0,"$18.00"],"60":["Plátano Tabasco[|]AGROELITE (FB: @AgroeliteMexico)",0,"$26.00"],"61":["Te-Limón (Lemon-Grass)[|]AGROELITE (FB: @AgroeliteMexico)",0,"$36.00"],"62":["Tomate Cherry[|]AGROELITE (FB: @AgroeliteMexico)",0,"$27.00"],"63":["Tomate Verde[|]AGROELITE (FB: @AgroeliteMexico)",0,"$29.00"],"64":["Zarzamora[|]AGROELITE (FB: @AgroeliteMexico)",0,"$90.00"],"65":["Zetas[|]AGROELITE (FB: @AgroeliteMexico)",0,"$33.00"],"66":["Acedera[|]EL JARDIN DEL AXOLOTE",0,"$16.00"],"67":["Flores Comestibles (20 piezas: mastuerzo, lavanda, hinojo, citronela, suspiros)[|]EL JARDIN DEL AXOLOTE",0,"$71.00"],"68":["HInojo de Hoja[|]EL JARDIN DEL AXOLOTE",0,"$16.00"],"69":["Lavanda[|]EL JARDIN DEL AXOLOTE",0,"$16.00"],"70":["Lechuga Mix (350 gr)[|]EL JARDIN DEL AXOLOTE",0,"$16.00"],"71":["Mastuerzo (hoja)[|]EL JARDIN DEL AXOLOTE",0,"$16.00"],"72":["Romero[|]EL JARDIN DEL AXOLOTE",0,"$16.00"],"73":["Ruda[|]EL JARDIN DEL AXOLOTE",0,"$16.00"],"74":["Toronjil[|]EL JARDIN DEL AXOLOTE",0,"$16.00"],"75":["Rindswurst (carne de res condimentada, tiene notas de ajo y paprika y es ligeramente picante; producto no agroecológico) 4 salchichas, aprox 800gr[|]CELESTIAL (@salchichascelestial)",0,"$200.00"],"76":["Salchichas Bratwurst (carne de cerdo con diez condimentos diferentes; producto no agroecológico) 4 salchichas, aprox 800gr[|]CELESTIAL (@salchichascelestial)",0,"$157.00"],"77":["Salchichas Schubling (carne de cerdo molida fina y condimento ligero, consistencia blanda y esponjosa; producto no agroecológico) 4 salchichas, aprox 800gr[|]CELESTIAL (@salchichascelestial)",0,"$157.00"],"78":["Weisswurst (carne de ternera, con notas de cebolla y perejil. Tiene color blanco, textura suave y se recomienda cocinar en agua caliente a fuego bajo; producto no agroecológivo) 4 salchichas, aprox 800gr[|]CELESTIAL (@salchichascelestial)",0,"$200.00"],"79":["Aderezo de Cúrcuma y Eneldo: raíz de cúrcuma frescas, hojas de eneldo frescas, ajo, vinagre, aceite multigrano, sal marina y diecisiete especias (265ml)[|]LA CUMBRE (FB: La Cumbre Conservas)",0,"$129.00"],"80":["Chimichurri Especiado: perejil, aceite multigrano, ajo, sal marina, vinagre y diecisiete especias (235gr)[|]LA CUMBRE (FB: La Cumbre Conservas)",0,"$129.00"],"81":["Pasta de Habanero: habaneros, ajo, jugo de limones, vinagre, especias y sal marina (120ml)[|]LA CUMBRE (FB: La Cumbre Conservas)",0,"$71.00"],"82":["Pesto de Albahaca: albahaca, nuez pecana, almendras, aceite de oliva primera extracción en frío, ajo y sal marina (235gr)[|]LA CUMBRE (FB: La Cumbre Conservas)",0,"$129.00"],"83":["Pesto de Cilantro: cilantro, almendras, cacahuates, aceite de oliva primera extracción en frío, ajo y sal marina (235gr)[|]LA CUMBRE (FB: La Cumbre Conservas)",0,"$129.00"],"84":["Salsa Huérfana: chipotles tostados a la leña, ajo, aceite multigrano y sal marina (250gr)[|]LA CUMBRE (FB: La Cumbre Conservas)",0,"$129.00"],"85":["Queso Mini Camembert[|]RANCHO 4 ENCINOS ( @ranchocuatroencinos)",0,"$86.00"],"86":["Queso Ricotta （250 gr）[|]RANCHO 4 ENCINOS ( @ranchocuatroencinos)",0,"$114.00"],"87":["Queso Ricotta Prensado （250 gr)[|]RANCHO 4 ENCINOS ( @ranchocuatroencinos)",0,"$114.00"],"88":["Queso Tipo Manchego Fresco (250 gr)[|]RANCHO 4 ENCINOS ( @ranchocuatroencinos)",0,"$64.00"],"89":["Queso Tipo Oaxaca (500gr)[|]RANCHO 4 ENCINOS ( @ranchocuatroencinos)",0,"$114.00"],"90":["Tortilla Mixta: amarilla, azul (1/2k empacadas al vacio)[|]MAIZAJO (@maizajo)",0,"$26.00"],"91":["Tostadas Comaleadas: cualquier color (15 piezas)[|]MAIZAJO (@maizajo)",0,"$36.00"],"92":["Cerveza Blanca de Maguey - IPA Blanca - 7% Alc. Vol. - cebada, miel de maguey, lúpulo, cascara de naranja agria, semilla de cilantro, levadura blanca.[|]MONSTRUO DE AGUA (@monstruo.de.agua) ",0,"$53.00"],"93":["Cerveza Sugoi - Clara - 5%Alc. Vol. - cebada, miel de maguey, jengibre, té limón, lúpulo, levadura.[|]MONSTRUO DE AGUA (@monstruo.de.agua) ",0,"$53.00"],"94":["Soda Probiótica Jengibre: jengibre fresco, te-verde y miel de caña orgánica fermentado con una levadura que genera ácidos orgánicos antioxidantes y una selección de 10 microorganismos benéficos. No es dulce; 20 calorías.[|]CHINAMPA(@chinampa.mx) ",0,"$40.00"],"95":["Soda Probiótica Te-Verde: te verde y miel de caña orgánica fermentado con una levadura que genera ácidos orgánicos antioxidantes y una selección de 10 microorganismos benéficos. No es dulce; 20 calorías.[|]CHINAMPA(@chinampa.mx) ",0,"$40.00"],"96":["Tintura madre de Cardamomo: aplica en gotas a bebidas o libremente en aderezos y platillos para aprovechar las cualidades aromáticas y medicinales de la hierba[|]CREATURAS BOTANICAS (@creaturasbotanicas)",0,"$133.00"],"97":["Tintura madre de Cedrón: aplica en gotas a bebidas o libremente en aderezos y platillos para aprovechar las cualidades aromáticas y medicinales de la hierba[|]CREATURAS BOTANICAS (@creaturasbotanicas)",0,"$133.00"],"98":["Tintura madre de Cempasúchil Silvestre: aplica en gotas a bebidas o libremente en aderezos y platillos para aprovechar las cualidades aromáticas y medicinales de la hierba[|]CREATURAS BOTANICAS (@creaturasbotanicas)",0,"$133.00"],"99":["Tintura madre de Curcuma: aplica en gotas a bebidas o libremente en aderezos y platillos para aprovechar las cualidades aromáticas y medicinales de la hierba[|]CREATURAS BOTANICAS (@creaturasbotanicas)",0,"$133.00"],"100":["Tintura madre de Equinacea: aplica en gotas a bebidas o libremente en aderezos y platillos para aprovechar las cualidades aromáticas y medicinales de la hierba[|]CREATURAS BOTANICAS (@creaturasbotanicas)",0,"$133.00"],"101":["Tintura madre de Gordolobo: aplica en gotas a bebidas o libremente en aderezos y platillos para aprovechar las cualidades aromáticas y medicinales de la hierba[|]CREATURAS BOTANICAS (@creaturasbotanicas)",0,"$133.00"],"102":["Tintura madre de Hoja de Higo: aplica en gotas a bebidas o libremente en aderezos y platillos para aprovechar las cualidades aromáticas y medicinales de la hierba[|]CREATURAS BOTANICAS (@creaturasbotanicas)",0,"$133.00"],"103":["Tintura madre de Hoja Santa: aplica en gotas a bebidas o libremente en aderezos y platillos para aprovechar las cualidades aromáticas y medicinales de la hierba[|]CREATURAS BOTANICAS (@creaturasbotanicas)",0,"$133.00"],"104":["Tintura madre de Jengibre Fresco: aplica en gotas a bebidas o libremente en aderezos y platillos para aprovechar las cualidades aromáticas y medicinales de la hierba[|]CREATURAS BOTANICAS (@creaturasbotanicas)",0,"$133.00"],"105":["Tintura madre de Toronjil: aplica en gotas a bebidas o libremente en aderezos y platillos para aprovechar las cualidades aromáticas y medicinales de la hierba[|]CREATURAS BOTANICAS (@creaturasbotanicas)",0,"$133.00"],"106":["Té Manzanilla-Lavanda: flores de manzanilla y lavanda (bolsa 30 gr, 15-18 tazas)[|]OHA (@oha.mx)",0,"$125.00"],"107":["Té Masala Chai: té negro, jengibre, canela, clavo, cardamomo y cacao (bolsa de 50 gr, 20-25 tazas)[|]OHA (@oha.mx)",0,"$160.00"],"108":["Té Verde-Limón: té verde (sencha), zacate limón y hierbabuena (bolsa de 50 gr, 20-25 tazas)[|]OHA (@oha.mx)",0,"$160.00"],"109":["Baguette (200gr): agua, sal, harina de trigo, masa madre[|]PARRILLA PARAISO ( @parrillaparaiso)",0,"$29.00"],"110":["Dulce de leche (235 ml)[|]PARRILLA PARAISO ( @parrillaparaiso)",0,"$114.00"],"111":["Hogaza (pan de campo 450gr): agua, harina de trigo, sal, masa madre[|]PARRILLA PARAISO ( @parrillaparaiso)",0,"$50.00"],"112":["Mermelada de Cebolla (235 ml)[|]PARRILLA PARAISO ( @parrillaparaiso)",0,"$93.00"],"113":["Mermelada de Fresa (235 ml)[|]PARRILLA PARAISO ( @parrillaparaiso)",0,"$100.00"],"114":["Mermelada de Jitomate (235 ml)[|]PARRILLA PARAISO ( @parrillaparaiso)",0,"$93.00"],"115":["Mermelada de Manzana (235 ml)[|]PARRILLA PARAISO ( @parrillaparaiso)",0,"$114.00"],"116":["Mermelada de Naranja (235 ml)[|]PARRILLA PARAISO ( @parrillaparaiso)",0,"$64.00"],"117":["Mermelada de Piña[|]PARRILLA PARAISO ( @parrillaparaiso)",0,"$86.00"],"118":["Pan de caja (750gr): leche, huevo, mantequilla, harina de trigo, azúcar, sal, levadura[|]PARRILLA PARAISO ( @parrillaparaiso)",0,"$93.00"],"119":["Pan de masa madre con granos de café y chocolate (250gr)[|]PARRILLA PARAISO ( @parrillaparaiso)",0,"$86.00"],"120":["Pasta Fresca Fettuccini (500gr): agua, semolina, harina de trigo, huevo, aceite, sal, levadura[|]PARRILLA PARAISO ( @parrillaparaiso)",0,"$71.00"],"121":["Bombones hechos en casa 160g [|]SAHUMERIO (@sahumeriocatering)",0,"$114.00"],"122":["Bombones hechos en casa de Lavanda 160g [|]SAHUMERIO (@sahumeriocatering)",0,"$114.00"],"123":["Mermelada de Guayaba 8 onz[|]SAHUMERIO (@sahumeriocatering)",0,"$114.00"],"124":["Monkeybutter 8 onz[|]SAHUMERIO (@sahumeriocatering)",0,"$114.00"],"125":["Barras de cereales - Paquetes de 5 - 160gr (VEGAN: arroz, avena, avellana, nuez corazon, arrandano, almendras, cacahuates, datiles) [|]ELSA",0,"$179.00"],"126":["Madeleines naturales y de chocolate - Paquetes de 6 (harina, mantequilla, azucar, miel, extracto de naranja amarga, huevo, bicarbonato de sodio, leche, cacao)[|]ELSA",0,"$129.00"],"127":["Panqué de limon amarillo con chia - 900gr (harina, mantequilla, azucar, limon amarillo, bicarbinato de sodio, chia, huevo)[|]ELSA",0,"$333.00"],"128":["Panqué de Mamey con platano - 650gr (harina, mantequilla, mascabado, mamey, platano, bicarbonato de sodio, sal, huevos)[|]ELSA",0,"$229.00"],"129":["Café en grano: Dark Side of the Fruit (250g)[|]CUCURUCHO @cucuruchocafe",0,"$193.00"],"130":["Café en grano: Veracruz (250g)[|]CUCURUCHO @cucuruchocafe",0,"$193.00"],"131":["Cafe en grano: Mezcla de la Casa (250g)[|]CUCURUCHO @cucuruchocafe",0,"$157.00"],"132":["Tapa Boca[|]CELIA ( @celiavermicelli)",0,"$114.00"],"133":["Canasta Pendiente (donación de una depensa para familias en comunidades marginadas, incluye frutas, verduras y granos)[|]PROYECTO CANASTA PENDIENTE",0,"$200.00"]}}